scrapy_plus/__init__.py
scrapy_plus/processors.py
scrapy_plus/dupefilters/__init__.py
scrapy_plus/dupefilters/redis.py
scrapy_plus/dupefilters/redisbloom.py
scrapy_plus/extensions/__init__.py
scrapy_plus/extensions/oss.py
scrapy_plus/extensions/sql.py
scrapy_plus/items/BookItem.py
scrapy_plus/items/NewsItem.py
scrapy_plus/items/ProductItem.py
scrapy_plus/items/__init__.py
scrapy_plus/middlewares/__init__.py
scrapy_plus/middlewares/autologin.py
scrapy_plus/middlewares/chrome.py
scrapy_plus/middlewares/huaban.py
scrapy_plus/middlewares/proxy.py
scrapy_plus/middlewares/splash.py
scrapy_plus/middlewares/tor.py
scrapy_plus/middlewares/ua.py
scrapy_plus/pipelines/__init__.py
scrapy_plus/pipelines/files.py
scrapy_plus/pipelines/images.py
scrapy_plus/pipelines/mongo.py
scrapy_plus/spiders/__init__.py
scrapy_plus/spiders/douban.py
scrapy_plus/spiders/netease.py
scrapy_plus/spiders/taobao.py
scrapy_plus/utils/__init__.py
scrapy_plus/utils/parser.py
scrapy_plus/utils/spiders.py
scrapy_plus/utils/starturls.py
scrapy_plus-1.0.5.dist-info/METADATA
scrapy_plus-1.0.5.dist-info/WHEEL
scrapy_plus-1.0.5.dist-info/top_level.txt
scrapy_plus-1.0.5.dist-info/RECORD
