Metadata-Version: 2.1
Name: scrapy-plus
Version: 1.0.5
Summary: scrapy 常用爬网必备工具包
Home-page: http://www.github.com/dotnetage/scrapy_plus
Author: Ray
Author-email: csharp2002@hotmail.com
License: BSD
Keywords: scrapy,crawl,redis,tor
Platform: any
Classifier: Development Status :: 4 - Beta
Classifier: Intended Audience :: Developers
Classifier: License :: OSI Approved :: BSD License
Classifier: Natural Language :: English
Classifier: Operating System :: OS Independent
Classifier: Programming Language :: Python :: 3.6
Classifier: Topic :: Software Development :: Libraries
Classifier: Topic :: Utilities
Requires-Dist: aliyun-python-sdk-core (==2.13.30)
Requires-Dist: aliyun-python-sdk-core-v3 (==2.13.11)
Requires-Dist: aliyun-python-sdk-kms (==2.13.0)
Requires-Dist: attrs (==20.3.0)
Requires-Dist: Automat (==20.2.0)
Requires-Dist: certifi (==2020.12.5)
Requires-Dist: cffi (==1.14.4)
Requires-Dist: chardet (==4.0.0)
Requires-Dist: constantly (==15.1.0)
Requires-Dist: crcmod (==1.7)
Requires-Dist: cryptography (==3.2.1)
Requires-Dist: cssselect (==1.1.0)
Requires-Dist: dateparser (==1.0.0)
Requires-Dist: hyperlink (==20.0.1)
Requires-Dist: idna (==2.10)
Requires-Dist: incremental (==17.5.0)
Requires-Dist: itemadapter (==0.2.0)
Requires-Dist: itemloaders (==1.0.4)
Requires-Dist: jmespath (==0.10.0)
Requires-Dist: lxml (==4.6.2)
Requires-Dist: oss2 (==2.13.1)
Requires-Dist: parsel (==1.6.0)
Requires-Dist: Protego (==0.1.16)
Requires-Dist: pyasn1 (==0.4.8)
Requires-Dist: pyasn1-modules (==0.2.8)
Requires-Dist: pycparser (==2.20)
Requires-Dist: pycryptodome (==3.9.9)
Requires-Dist: PyDispatcher (==2.0.5)
Requires-Dist: PyHamcrest (==2.0.2)
Requires-Dist: pymongo (==3.11.2)
Requires-Dist: pyOpenSSL (==20.0.1)
Requires-Dist: python-dateutil (==2.8.1)
Requires-Dist: pytz (==2020.4)
Requires-Dist: queuelib (==1.5.0)
Requires-Dist: redis (==3.5.3)
Requires-Dist: regex (==2020.11.13)
Requires-Dist: requests (==2.25.1)
Requires-Dist: Scrapy (==2.4.1)
Requires-Dist: scrapy-splash (==0.7.2)
Requires-Dist: selenium (==3.141.0)
Requires-Dist: service-identity (==18.1.0)
Requires-Dist: six (==1.15.0)
Requires-Dist: SQLAlchemy (==1.3.20)
Requires-Dist: stem (==1.8.0)
Requires-Dist: Twisted (==20.3.0)
Requires-Dist: tzlocal (==2.1)
Requires-Dist: urllib3 (==1.26.2)
Requires-Dist: w3lib (==1.22.0)
Requires-Dist: zope.interface (==5.2.0)
